{"users":[{"id":55450157.82641668,"firstName":"ex in eu sint enim","lastName":"dolor","email":"Excepteur cillum"},{"id":53915380.52381188,"firstName":"proident nisi consequat Ut","lastName":"ea officia","email":"non cillum occaecat"},{"id":1517930.5548087012,"firstName":"ad sint consectetur dolore non","lastName":"fugiat","email":"cupidatat in nisi"},{"id":61183268.750506364,"firstName":"cupidatat","lastName":"tempor","email":"ullamco et anim fugiat"},{"id":60847993.97262339,"firstName":"aliquip","lastName":"officia reprehenderit anim nostrud consectetur","email":"ipsum"}]}